cdk_sns_notify/__init__.py
cdk_sns_notify/py.typed
cdk_sns_notify/_jsii/__init__.py
cdk_sns_notify/_jsii/cdk-sns-notify@0.0.948.jsii.tgz
cdk_sns_notify-0.0.948.dist-info/LICENSE
cdk_sns_notify-0.0.948.dist-info/METADATA
cdk_sns_notify-0.0.948.dist-info/WHEEL
cdk_sns_notify-0.0.948.dist-info/top_level.txt
cdk_sns_notify-0.0.948.dist-info/RECORD
